LICENSE
MANIFEST.in
README.rst
setup.cfg
setup.py
versioneer.py
tpDcc/__init__.py
tpDcc/libs/__init__.py
tpDcc/libs/psd/__init__.py
tpDcc/libs/psd/__logging__.ini
tpDcc/libs/psd/__version__.py
tpDcc/libs/psd/_version.py
tpDcc/libs/psd/core/__init__.py
tpDcc/libs/psd/core/consts.py
tpDcc/libs/psd/core/document.py
tpDcc/libs/psd/core/sequence.py
tpDcc_libs_psd.egg-info/PKG-INFO
tpDcc_libs_psd.egg-info/SOURCES.txt
tpDcc_libs_psd.egg-info/dependency_links.txt
tpDcc_libs_psd.egg-info/not-zip-safe
tpDcc_libs_psd.egg-info/requires.txt
tpDcc_libs_psd.egg-info/top_level.txt