Metadata-Version: 2.1
Name: tpDcc-libs-psd
Version: 0.0.1
Summary: Library that contains functions to interact with Photoshop files.
Home-page: https://github.com/tpDcc/tpDcc-libs-psd
Author: Tomas Poveda
Author-email: tpovedatd@gmail.com
License: MIT
Platform: UNKNOWN
Provides-Extra: dev
Provides-Extra: test
